lightmail/__init__.py
lightmail/email.py
lightmail/utils.py
lightmail-1.0.0.dist-info/LICENSE
lightmail-1.0.0.dist-info/METADATA
lightmail-1.0.0.dist-info/WHEEL
lightmail-1.0.0.dist-info/top_level.txt
lightmail-1.0.0.dist-info/RECORD
