Metadata-Version: 2.1
Name: lightmail
Version: 1.0.0
Summary: Send Email for Python
Home-page: https://github.com/ni-ning/lightmail
Author: ni-ning
Author-email: nining1314@gmail.com
License: UNKNOWN
Keywords: email,smtplib,lightmail
Platform: UNKNOWN
Classifier: Development Status :: 3 - Alpha
Classifier: Intended Audience :: Developers
Classifier: License :: OSI Approved :: MIT License
Classifier: Programming Language :: Python :: 2
Classifier: Programming Language :: Python :: 2.7
Classifier: Programming Language :: Python :: 3
Classifier: Programming Language :: Python :: 3.3
Classifier: Programming Language :: Python :: 3.4
Classifier: Programming Language :: Python :: 3.5
Classifier: Programming Language :: Python :: 3.6
Classifier: Programming Language :: Python :: 3.7
Requires-Dist: six
